ggpy2/__init__.py
ggpy2-0.0.1.dist-info/METADATA
ggpy2-0.0.1.dist-info/WHEEL
ggpy2-0.0.1.dist-info/top_level.txt
ggpy2-0.0.1.dist-info/RECORD
